{
  "realm": "gryt",
  "enabled": true,
  "displayName": "Gryt",
  "registrationAllowed": false,
  "resetPasswordAllowed": true,
  "loginWithEmailAllowed": true,
  "registrationEmailAsUsername": true,
  "duplicateEmailsAllowed": false,
  "rememberMe": true,
  "verifyEmail": true,
  "loginTheme": "gryt",
  "emailTheme": "gryt",
  "smtpServer": {
    "host": "__GRYT_SMTP_HOST__",
    "port": "__GRYT_SMTP_PORT__",
    "from": "__GRYT_SMTP_FROM__",
    "fromDisplayName": "__GRYT_SMTP_FROM_NAME__",
    "replyTo": "__GRYT_SMTP_REPLY_TO__",
    "replyToDisplayName": "__GRYT_SMTP_REPLY_TO_NAME__",
    "envelopeFrom": "",
    "starttls": "true",
    "ssl": "false",
    "auth": "true",
    "user": "__GRYT_SMTP_USER__",
    "password": "__GRYT_SMTP_PASS__",
    "debug": "false"
  },
  "ssoSessionIdleTimeout": 604800,
  "ssoSessionMaxLifespan": 2592000,
  "offlineSessionIdleTimeout": 2592000,
  "offlineSessionMaxLifespan": 7776000,
  "accessTokenLifespan": 300,
  "sslRequired": "external",

  "webAuthnPolicyPasswordlessRpEntityName": "Gryt",
  "webAuthnPolicyPasswordlessRpId": "",
  "webAuthnPolicyPasswordlessSignatureAlgorithms": ["ES256"],
  "webAuthnPolicyPasswordlessAttestationConveyancePreference": "not specified",
  "webAuthnPolicyPasswordlessAuthenticatorAttachment": "not specified",
  "webAuthnPolicyPasswordlessRequireResidentKey": "Yes",
  "webAuthnPolicyPasswordlessUserVerificationRequirement": "required",
  "webAuthnPolicyPasswordlessCreateTimeout": 0,
  "webAuthnPolicyPasswordlessAvoidSameAuthenticatorRegister": true,
  "webAuthnPolicyPasswordlessAcceptableAaguids": [],

  "browserFlow": "gryt browser",

  "authenticationFlows": [
    {
      "alias": "gryt browser",
      "description": "Browser-based authentication with passkey support",
      "providerId": "basic-flow",
      "topLevel": true,
      "builtIn": false,
      "authenticationExecutions": [
        {
          "authenticator": "auth-cookie",
          "authenticatorFlow": false,
          "requirement": "ALTERNATIVE",
          "priority": 10,
          "userSetupAllowed": false
        },
        {
          "authenticator": "identity-provider-redirector",
          "authenticatorFlow": false,
          "requirement": "ALTERNATIVE",
          "priority": 20,
          "userSetupAllowed": false
        },
        {
          "authenticator": "webauthn-authenticator-passwordless",
          "authenticatorFlow": false,
          "requirement": "ALTERNATIVE",
          "priority": 30,
          "userSetupAllowed": false
        },
        {
          "authenticatorFlow": true,
          "requirement": "ALTERNATIVE",
          "priority": 40,
          "flowAlias": "gryt browser forms",
          "userSetupAllowed": false
        }
      ]
    },
    {
      "alias": "gryt browser forms",
      "description": "Username and password form",
      "providerId": "basic-flow",
      "topLevel": false,
      "builtIn": false,
      "authenticationExecutions": [
        {
          "authenticator": "auth-username-password-form",
          "authenticatorFlow": false,
          "requirement": "REQUIRED",
          "priority": 10,
          "userSetupAllowed": false
        }
      ]
    }
  ],

  "requiredActions": [
    {
      "alias": "CONFIGURE_TOTP",
      "name": "Configure OTP",
      "providerId": "CONFIGURE_TOTP",
      "enabled": true,
      "defaultAction": false,
      "priority": 10,
      "config": {}
    },
    {
      "alias": "UPDATE_PASSWORD",
      "name": "Update Password",
      "providerId": "UPDATE_PASSWORD",
      "enabled": true,
      "defaultAction": false,
      "priority": 30,
      "config": {}
    },
    {
      "alias": "VERIFY_EMAIL",
      "name": "Verify Email",
      "providerId": "VERIFY_EMAIL",
      "enabled": true,
      "defaultAction": false,
      "priority": 50,
      "config": {}
    },
    {
      "alias": "update_user_locale",
      "name": "Update User Locale",
      "providerId": "update_user_locale",
      "enabled": true,
      "defaultAction": false,
      "priority": 60,
      "config": {}
    },
    {
      "alias": "webauthn-register-passwordless",
      "name": "Webauthn Register Passwordless",
      "providerId": "webauthn-register-passwordless",
      "enabled": true,
      "defaultAction": false,
      "priority": 70,
      "config": {}
    },
    {
      "alias": "delete_account",
      "name": "Delete Account",
      "providerId": "delete_account",
      "enabled": false,
      "defaultAction": false,
      "priority": 80,
      "config": {}
    }
  ],

  "clients": [
    {
      "clientId": "gryt-web",
      "name": "Gryt Web Client",
      "enabled": true,
      "protocol": "openid-connect",
      "publicClient": true,
      "standardFlowEnabled": true,
      "implicitFlowEnabled": false,
      "directAccessGrantsEnabled": false,
      "serviceAccountsEnabled": false,
      "frontchannelLogout": true,
      "redirectUris": [
        "https://gryt.chat/*",
        "https://app.gryt.chat/*",
        "https://beta.gryt.chat/*",
        "https://gryt.example.com/*",
        "http://localhost:3666/*",
        "http://localhost:3667/*",
        "http://127.0.0.1:15738/*",
        "gryt://auth/callback"
      ],
      "webOrigins": [
        "https://gryt.chat",
        "https://app.gryt.chat",
        "https://beta.gryt.chat",
        "https://gryt.example.com",
        "http://localhost:3666",
        "http://localhost:3667",
        "http://127.0.0.1:15738"
      ],
      "attributes": {
        "pkce.code.challenge.method": "S256"
      }
    }
  ]
}

